[{"timestamp":"2023-10-24T00:54:42.404Z","count":0,"uniques":0},{"timestamp":"2023-10-25T00:49:19.588Z","count":0,"uniques":0},{"timestamp":"2023-10-26T00:52:03.077Z","count":0,"uniques":0},{"timestamp":"2023-10-27T00:48:44.036Z","count":0,"uniques":0},{"timestamp":"2023-10-28T00:48:38.674Z","count":0,"uniques":0},{"timestamp":"2023-10-29T00:00:00.000Z","count":7,"uniques":1},{"timestamp":"2023-10-30T00:50:57.054Z","count":0,"uniques":0},{"timestamp":"2023-10-31T00:52:09.608Z","count":0,"uniques":0},{"timestamp":"2023-11-01T00:57:49.466Z","count":0,"uniques":0},{"timestamp":"2023-11-02T00:50:56.712Z","count":0,"uniques":0},{"timestamp":"2023-11-03T00:51:19.571Z","count":0,"uniques":0},{"timestamp":"2023-11-04T00:50:13.047Z","count":0,"uniques":0},{"timestamp":"2023-11-05T00:58:14.358Z","count":0,"uniques":0},{"timestamp":"2023-11-06T00:48:42.071Z","count":0,"uniques":0},{"timestamp":"2023-11-07T00:55:26.372Z","count":0,"uniques":0},{"timestamp":"2023-11-08T00:48:00.472Z","count":0,"uniques":0},{"timestamp":"2023-11-09T00:48:39.888Z","count":0,"uniques":0},{"timestamp":"2023-11-10T00:54:11.792Z","count":0,"uniques":0},{"timestamp":"2023-11-11T00:55:28.204Z","count":0,"uniques":0},{"timestamp":"2023-11-12T00:51:03.986Z","count":0,"uniques":0},{"timestamp":"2023-11-13T00:49:02.048Z","count":0,"uniques":0},{"timestamp":"2023-11-14T00:50:55.961Z","count":0,"uniques":0},{"timestamp":"2023-11-15T00:48:43.873Z","count":0,"uniques":0},{"timestamp":"2023-11-16T00:00:00.000Z","count":1,"uniques":1},{"timestamp":"2023-11-17T00:49:55.451Z","count":0,"uniques":0},{"timestamp":"2023-11-18T00:48:45.872Z","count":0,"uniques":0},{"timestamp":"2023-11-19T00:52:54.470Z","count":0,"uniques":0},{"timestamp":"2023-11-20T00:49:54.733Z","count":0,"uniques":0},{"timestamp":"2023-11-21T00:49:57.597Z","count":0,"uniques":0},{"timestamp":"2023-11-22T00:51:04.306Z","count":0,"uniques":0},{"timestamp":"2023-11-23T00:49:04.872Z","count":0,"uniques":0}]
