[{"timestamp":"2024-09-28T01:04:10.539Z","count":0,"uniques":0},{"timestamp":"2024-09-29T01:06:53.425Z","count":0,"uniques":0},{"timestamp":"2024-09-30T01:04:19.826Z","count":0,"uniques":0},{"timestamp":"2024-10-01T01:07:27.356Z","count":0,"uniques":0},{"timestamp":"2024-10-02T05:16:52.190Z","count":0,"uniques":0},{"timestamp":"2024-10-03T01:02:04.911Z","count":0,"uniques":0},{"timestamp":"2024-10-04T01:03:21.249Z","count":0,"uniques":0},{"timestamp":"2024-10-05T01:01:51.827Z","count":0,"uniques":0}]
