[{"timestamp":"2025-05-31T01:02:30.860Z","count":0,"uniques":0},{"timestamp":"2025-06-01T01:15:23.786Z","count":0,"uniques":0},{"timestamp":"2025-06-02T01:06:09.925Z","count":0,"uniques":0},{"timestamp":"2025-06-03T01:04:55.997Z","count":0,"uniques":0},{"timestamp":"2025-06-04T01:04:24.633Z","count":0,"uniques":0},{"timestamp":"2025-06-05T06:22:13.063Z","count":0,"uniques":0},{"timestamp":"2025-06-06T01:04:04.620Z","count":0,"uniques":0},{"timestamp":"2025-06-07T01:03:25.184Z","count":0,"uniques":0}]
