[{"timestamp":"2023-10-13T14:38:43.829Z","count":0,"uniques":0},{"timestamp":"2023-10-14T14:38:43.829Z","count":0,"uniques":0},{"timestamp":"2023-10-15T14:38:43.829Z","count":0,"uniques":0},{"timestamp":"2023-10-16T14:38:43.829Z","count":0,"uniques":0},{"timestamp":"2023-10-17T14:38:43.829Z","count":0,"uniques":0},{"timestamp":"2023-10-18T14:38:43.829Z","count":0,"uniques":0},{"timestamp":"2023-10-19T14:38:43.829Z","count":0,"uniques":0},{"timestamp":"2023-10-20T00:40:18.984Z","count":0,"uniques":0}]
