[{"timestamp":"2024-04-16T00:41:02.372Z","count":0,"uniques":0},{"timestamp":"2024-04-17T00:42:22.780Z","count":0,"uniques":0},{"timestamp":"2024-04-18T00:41:36.827Z","count":0,"uniques":0},{"timestamp":"2024-04-19T00:42:04.449Z","count":0,"uniques":0},{"timestamp":"2024-04-20T00:42:01.200Z","count":0,"uniques":0},{"timestamp":"2024-04-21T00:45:01.214Z","count":0,"uniques":0},{"timestamp":"2024-04-22T00:43:37.226Z","count":0,"uniques":0},{"timestamp":"2024-04-23T00:41:57.116Z","count":0,"uniques":0}]
