[{"timestamp":"2024-05-15T00:52:42.301Z","count":0,"uniques":0},{"timestamp":"2024-05-16T00:52:59.212Z","count":0,"uniques":0},{"timestamp":"2024-05-17T00:52:54.787Z","count":0,"uniques":0},{"timestamp":"2024-05-18T00:52:52.221Z","count":0,"uniques":0},{"timestamp":"2024-05-19T00:57:51.900Z","count":0,"uniques":0},{"timestamp":"2024-05-20T00:54:31.599Z","count":0,"uniques":0},{"timestamp":"2024-05-21T00:53:32.355Z","count":0,"uniques":0},{"timestamp":"2024-05-22T00:53:38.745Z","count":0,"uniques":0}]
