[{"timestamp":"2024-09-16T01:09:47.128Z","count":0,"uniques":0},{"timestamp":"2024-09-17T00:58:01.794Z","count":0,"uniques":0},{"timestamp":"2024-09-18T01:06:22.716Z","count":0,"uniques":0},{"timestamp":"2024-09-19T01:05:20.408Z","count":0,"uniques":0},{"timestamp":"2024-09-20T01:05:44.039Z","count":0,"uniques":0},{"timestamp":"2024-09-21T01:04:35.859Z","count":0,"uniques":0},{"timestamp":"2024-09-22T01:10:54.200Z","count":0,"uniques":0},{"timestamp":"2024-09-23T01:07:21.673Z","count":0,"uniques":0}]
