[{"timestamp":"2025-09-28T01:18:04.831Z","count":0,"uniques":0},{"timestamp":"2025-09-29T01:13:42.908Z","count":0,"uniques":0},{"timestamp":"2025-09-30T01:12:09.639Z","count":0,"uniques":0},{"timestamp":"2025-10-01T01:19:41.442Z","count":0,"uniques":0},{"timestamp":"2025-10-02T01:11:02.391Z","count":0,"uniques":0},{"timestamp":"2025-10-03T01:11:24.476Z","count":0,"uniques":0},{"timestamp":"2025-10-04T01:09:25.211Z","count":0,"uniques":0},{"timestamp":"2025-10-05T01:16:47.354Z","count":0,"uniques":0}]
