[{"timestamp":"2024-06-22T00:42:56.339Z","count":0,"uniques":0},{"timestamp":"2024-06-23T00:46:56.142Z","count":0,"uniques":0},{"timestamp":"2024-06-24T00:45:21.231Z","count":0,"uniques":0},{"timestamp":"2024-06-25T00:43:39.820Z","count":0,"uniques":0},{"timestamp":"2024-06-26T00:43:46.451Z","count":0,"uniques":0},{"timestamp":"2024-06-27T00:44:08.801Z","count":0,"uniques":0},{"timestamp":"2024-06-28T00:44:18.369Z","count":0,"uniques":0},{"timestamp":"2024-06-29T00:43:09.208Z","count":0,"uniques":0},{"timestamp":"2024-06-30T00:48:43.927Z","count":0,"uniques":0},{"timestamp":"2024-07-01T00:50:37.048Z","count":0,"uniques":0},{"timestamp":"2024-07-02T00:44:36.422Z","count":0,"uniques":0},{"timestamp":"2024-07-03T00:44:09.203Z","count":0,"uniques":0},{"timestamp":"2024-07-04T00:44:44.919Z","count":0,"uniques":0},{"timestamp":"2024-07-05T00:44:09.052Z","count":0,"uniques":0},{"timestamp":"2024-07-06T00:42:55.245Z","count":0,"uniques":0},{"timestamp":"2024-07-07T00:48:54.770Z","count":0,"uniques":0},{"timestamp":"2024-07-08T00:46:06.012Z","count":0,"uniques":0},{"timestamp":"2024-07-09T00:44:44.374Z","count":0,"uniques":0},{"timestamp":"2024-07-10T00:45:13.170Z","count":0,"uniques":0},{"timestamp":"2024-07-11T00:45:56.507Z","count":0,"uniques":0},{"timestamp":"2024-07-12T00:44:35.532Z","count":0,"uniques":0},{"timestamp":"2024-07-13T00:45:34.138Z","count":0,"uniques":0},{"timestamp":"2024-07-14T00:50:19.121Z","count":0,"uniques":0},{"timestamp":"2024-07-15T00:47:05.836Z","count":0,"uniques":0},{"timestamp":"2024-07-16T00:45:37.669Z","count":0,"uniques":0},{"timestamp":"2024-07-17T00:46:07.017Z","count":0,"uniques":0},{"timestamp":"2024-07-18T00:46:05.088Z","count":0,"uniques":0},{"timestamp":"2024-07-19T01:59:10.851Z","count":0,"uniques":0},{"timestamp":"2024-07-20T00:44:37.458Z","count":0,"uniques":0},{"timestamp":"2024-07-21T00:50:02.994Z","count":0,"uniques":0},{"timestamp":"2024-07-22T00:47:26.235Z","count":0,"uniques":0}]
