[{"timestamp":"2026-04-04T00:00:00.000Z","count":1,"uniques":1},{"timestamp":"2026-04-05T01:46:40.891Z","count":0,"uniques":0},{"timestamp":"2026-04-06T00:00:00.000Z","count":1,"uniques":1},{"timestamp":"2026-04-07T01:31:17.354Z","count":0,"uniques":0},{"timestamp":"2026-04-08T01:45:40.715Z","count":0,"uniques":0},{"timestamp":"2026-04-09T01:24:50.514Z","count":0,"uniques":0},{"timestamp":"2026-04-10T01:48:49.125Z","count":0,"uniques":0},{"timestamp":"2026-04-11T01:27:23.892Z","count":0,"uniques":0}]
