[{"timestamp":"2025-08-27T01:15:53.612Z","count":0,"uniques":0},{"timestamp":"2025-08-28T01:15:07.465Z","count":0,"uniques":0},{"timestamp":"2025-08-29T01:15:35.302Z","count":0,"uniques":0},{"timestamp":"2025-08-30T01:13:57.448Z","count":0,"uniques":0},{"timestamp":"2025-08-31T01:19:34.731Z","count":0,"uniques":0},{"timestamp":"2025-09-01T01:26:11.579Z","count":0,"uniques":0},{"timestamp":"2025-09-02T01:17:08.882Z","count":0,"uniques":0},{"timestamp":"2025-09-03T01:12:32.398Z","count":0,"uniques":0}]
