[{"timestamp":"2024-06-18T00:59:27.243Z","count":0,"uniques":0},{"timestamp":"2024-06-19T01:01:34.489Z","count":0,"uniques":0},{"timestamp":"2024-06-20T01:00:09.810Z","count":0,"uniques":0},{"timestamp":"2024-06-21T00:58:12.319Z","count":0,"uniques":0},{"timestamp":"2024-06-22T00:58:08.455Z","count":0,"uniques":0},{"timestamp":"2024-06-23T01:02:15.090Z","count":0,"uniques":0},{"timestamp":"2024-06-24T01:01:23.382Z","count":0,"uniques":0},{"timestamp":"2024-06-25T00:59:22.799Z","count":0,"uniques":0}]
