[{"timestamp":"2024-05-12T01:00:43.507Z","count":0,"uniques":0},{"timestamp":"2024-05-13T00:57:51.334Z","count":0,"uniques":0},{"timestamp":"2024-05-14T00:57:07.216Z","count":0,"uniques":0},{"timestamp":"2024-05-15T00:57:09.684Z","count":0,"uniques":0},{"timestamp":"2024-05-16T00:57:48.992Z","count":0,"uniques":0},{"timestamp":"2024-05-17T00:57:22.538Z","count":0,"uniques":0},{"timestamp":"2024-05-18T00:57:31.187Z","count":0,"uniques":0},{"timestamp":"2024-05-19T01:02:53.071Z","count":0,"uniques":0}]
