[{"timestamp":"2025-10-15T01:03:16.657Z","count":0,"uniques":0},{"timestamp":"2025-10-16T01:02:09.165Z","count":0,"uniques":0},{"timestamp":"2025-10-17T01:02:09.955Z","count":0,"uniques":0},{"timestamp":"2025-10-18T00:00:00.000Z","count":1,"uniques":1},{"timestamp":"2025-10-19T01:08:57.923Z","count":0,"uniques":0},{"timestamp":"2025-10-20T01:06:42.658Z","count":0,"uniques":0},{"timestamp":"2025-10-21T01:03:37.007Z","count":0,"uniques":0},{"timestamp":"2025-10-22T01:04:31.020Z","count":0,"uniques":0}]
