[{"timestamp":"2023-10-25T00:40:35.010Z","count":0,"uniques":0},{"timestamp":"2023-10-26T00:40:58.145Z","count":0,"uniques":0},{"timestamp":"2023-10-27T00:39:57.946Z","count":0,"uniques":0},{"timestamp":"2023-10-28T00:39:41.388Z","count":0,"uniques":0},{"timestamp":"2023-10-29T00:43:27.038Z","count":0,"uniques":0},{"timestamp":"2023-10-30T00:41:42.157Z","count":0,"uniques":0},{"timestamp":"2023-10-31T00:42:02.938Z","count":0,"uniques":0},{"timestamp":"2023-11-01T00:45:26.895Z","count":0,"uniques":0}]
