[{"timestamp":"2025-02-24T00:54:10.421Z","count":0,"uniques":0},{"timestamp":"2025-02-25T00:53:22.819Z","count":0,"uniques":0},{"timestamp":"2025-02-26T00:53:21.512Z","count":0,"uniques":0},{"timestamp":"2025-02-27T00:53:12.123Z","count":0,"uniques":0},{"timestamp":"2025-02-28T00:53:30.683Z","count":0,"uniques":0},{"timestamp":"2025-03-01T00:57:40.844Z","count":0,"uniques":0},{"timestamp":"2025-03-02T00:56:52.100Z","count":0,"uniques":0},{"timestamp":"2025-03-03T00:55:16.842Z","count":0,"uniques":0}]
