[{"timestamp":"2024-06-30T00:46:52.997Z","count":0,"uniques":0},{"timestamp":"2024-07-01T00:48:59.738Z","count":0,"uniques":0},{"timestamp":"2024-07-02T00:42:41.097Z","count":0,"uniques":0},{"timestamp":"2024-07-03T00:42:32.349Z","count":0,"uniques":0},{"timestamp":"2024-07-04T00:42:53.376Z","count":0,"uniques":0},{"timestamp":"2024-07-05T00:42:29.193Z","count":0,"uniques":0},{"timestamp":"2024-07-06T00:41:18.633Z","count":0,"uniques":0},{"timestamp":"2024-07-07T00:47:18.315Z","count":0,"uniques":0}]
