[{"timestamp":"2026-03-11T01:28:20.315Z","count":0,"uniques":0},{"timestamp":"2026-03-12T01:27:54.835Z","count":0,"uniques":0},{"timestamp":"2026-03-13T01:32:03.347Z","count":0,"uniques":0},{"timestamp":"2026-03-14T01:31:01.743Z","count":0,"uniques":0},{"timestamp":"2026-03-15T01:42:27.721Z","count":0,"uniques":0},{"timestamp":"2026-03-16T01:42:35.582Z","count":0,"uniques":0},{"timestamp":"2026-03-17T01:34:46.904Z","count":0,"uniques":0},{"timestamp":"2026-03-18T01:37:28.650Z","count":0,"uniques":0}]
