[{"timestamp":"2025-10-06T01:21:28.518Z","count":0,"uniques":0},{"timestamp":"2025-10-07T01:20:32.738Z","count":0,"uniques":0},{"timestamp":"2025-10-08T01:20:18.049Z","count":0,"uniques":0},{"timestamp":"2025-10-09T01:21:47.952Z","count":0,"uniques":0},{"timestamp":"2025-10-10T01:21:33.737Z","count":0,"uniques":0},{"timestamp":"2025-10-11T01:20:15.372Z","count":0,"uniques":0},{"timestamp":"2025-10-12T01:25:28.478Z","count":0,"uniques":0},{"timestamp":"2025-10-13T01:25:08.018Z","count":0,"uniques":0},{"timestamp":"2025-10-14T01:21:58.893Z","count":0,"uniques":0},{"timestamp":"2025-10-15T01:25:27.166Z","count":0,"uniques":0},{"timestamp":"2025-10-16T01:23:42.783Z","count":0,"uniques":0},{"timestamp":"2025-10-17T01:22:47.320Z","count":0,"uniques":0},{"timestamp":"2025-10-18T01:20:35.386Z","count":0,"uniques":0},{"timestamp":"2025-10-19T01:29:34.373Z","count":0,"uniques":0},{"timestamp":"2025-10-20T01:27:00.772Z","count":0,"uniques":0},{"timestamp":"2025-10-21T01:24:37.745Z","count":0,"uniques":0},{"timestamp":"2025-10-22T01:24:51.301Z","count":0,"uniques":0},{"timestamp":"2025-10-23T01:23:49.518Z","count":0,"uniques":0},{"timestamp":"2025-10-24T01:20:02.051Z","count":0,"uniques":0},{"timestamp":"2025-10-25T01:22:01.386Z","count":0,"uniques":0},{"timestamp":"2025-10-26T01:26:54.732Z","count":0,"uniques":0},{"timestamp":"2025-10-27T01:29:07.994Z","count":0,"uniques":0},{"timestamp":"2025-10-28T01:23:14.603Z","count":0,"uniques":0},{"timestamp":"2025-10-29T01:26:49.628Z","count":0,"uniques":0},{"timestamp":"2025-10-30T01:26:37.408Z","count":0,"uniques":0},{"timestamp":"2025-10-31T01:24:07.887Z","count":0,"uniques":0},{"timestamp":"2025-11-01T01:29:10.048Z","count":0,"uniques":0},{"timestamp":"2025-11-02T01:28:50.449Z","count":0,"uniques":0},{"timestamp":"2025-11-03T01:27:02.320Z","count":0,"uniques":0},{"timestamp":"2025-11-04T01:26:06.773Z","count":0,"uniques":0},{"timestamp":"2025-11-05T01:27:53.958Z","count":0,"uniques":0}]
