[{"timestamp":"2024-10-11T00:59:35.372Z","count":0,"uniques":0},{"timestamp":"2024-10-12T00:58:16.514Z","count":0,"uniques":0},{"timestamp":"2024-10-13T01:03:45.633Z","count":0,"uniques":0},{"timestamp":"2024-10-14T01:01:42.722Z","count":0,"uniques":0},{"timestamp":"2024-10-15T01:00:41.197Z","count":0,"uniques":0},{"timestamp":"2024-10-16T01:00:51.945Z","count":0,"uniques":0},{"timestamp":"2024-10-17T01:00:10.918Z","count":0,"uniques":0},{"timestamp":"2024-10-18T01:00:22.101Z","count":0,"uniques":0}]
