[{"timestamp":"2024-04-01T00:50:09.308Z","count":0,"uniques":0},{"timestamp":"2024-04-02T00:50:07.133Z","count":0,"uniques":0},{"timestamp":"2024-04-03T00:45:37.188Z","count":0,"uniques":0},{"timestamp":"2024-04-04T00:48:46.026Z","count":0,"uniques":0},{"timestamp":"2024-04-05T00:46:42.242Z","count":0,"uniques":0},{"timestamp":"2024-04-06T00:45:19.169Z","count":0,"uniques":0},{"timestamp":"2024-04-07T00:50:19.819Z","count":0,"uniques":0},{"timestamp":"2024-04-08T00:47:32.479Z","count":0,"uniques":0}]
