[{"timestamp":"2024-11-04T01:14:05.909Z","count":0,"uniques":0},{"timestamp":"2024-11-05T01:12:43.218Z","count":0,"uniques":0},{"timestamp":"2024-11-06T01:13:05.761Z","count":0,"uniques":0},{"timestamp":"2024-11-07T01:13:17.262Z","count":0,"uniques":0},{"timestamp":"2024-11-08T01:10:20.139Z","count":0,"uniques":0},{"timestamp":"2024-11-09T01:11:29.973Z","count":0,"uniques":0},{"timestamp":"2024-11-10T01:14:54.070Z","count":0,"uniques":0},{"timestamp":"2024-11-11T01:12:48.882Z","count":0,"uniques":0}]
