[{"timestamp":"2026-05-17T02:39:46.628Z","count":0,"uniques":0},{"timestamp":"2026-05-18T00:00:00.000Z","count":2,"uniques":2},{"timestamp":"2026-05-19T03:00:18.994Z","count":0,"uniques":0},{"timestamp":"2026-05-20T02:56:54.034Z","count":0,"uniques":0},{"timestamp":"2026-05-21T03:00:31.200Z","count":0,"uniques":0},{"timestamp":"2026-05-22T03:02:22.728Z","count":0,"uniques":0},{"timestamp":"2026-05-23T02:36:49.690Z","count":0,"uniques":0},{"timestamp":"2026-05-24T02:54:47.679Z","count":0,"uniques":0}]
