[{"timestamp":"2024-01-23T01:04:14.750Z","count":0,"uniques":0},{"timestamp":"2024-01-24T01:04:59.608Z","count":0,"uniques":0},{"timestamp":"2024-01-25T01:03:57.505Z","count":0,"uniques":0},{"timestamp":"2024-01-26T01:03:36.806Z","count":0,"uniques":0},{"timestamp":"2024-01-27T01:02:21.750Z","count":0,"uniques":0},{"timestamp":"2024-01-28T01:05:14.741Z","count":0,"uniques":0},{"timestamp":"2024-01-29T01:01:25.927Z","count":0,"uniques":0},{"timestamp":"2024-01-30T01:00:15.064Z","count":0,"uniques":0}]
