[{"timestamp":"2024-11-19T01:20:37.283Z","count":0,"uniques":0},{"timestamp":"2024-11-20T01:20:32.957Z","count":0,"uniques":0},{"timestamp":"2024-11-21T01:19:41.410Z","count":0,"uniques":0},{"timestamp":"2024-11-22T01:24:46.392Z","count":0,"uniques":0},{"timestamp":"2024-11-23T01:21:47.517Z","count":0,"uniques":0},{"timestamp":"2024-11-24T01:24:17.455Z","count":0,"uniques":0},{"timestamp":"2024-11-25T01:21:48.698Z","count":0,"uniques":0},{"timestamp":"2024-11-26T01:20:00.872Z","count":0,"uniques":0}]
