[{"timestamp":"2026-06-30T02:37:39.396Z","count":0,"uniques":0},{"timestamp":"2026-07-01T02:43:26.364Z","count":0,"uniques":0},{"timestamp":"2026-07-02T02:32:58.746Z","count":0,"uniques":0},{"timestamp":"2026-07-03T02:08:46.076Z","count":0,"uniques":0},{"timestamp":"2026-07-04T02:06:15.724Z","count":0,"uniques":0},{"timestamp":"2026-07-05T02:14:55.385Z","count":0,"uniques":0},{"timestamp":"2026-07-06T02:26:23.961Z","count":0,"uniques":0},{"timestamp":"2026-07-07T02:14:58.822Z","count":0,"uniques":0}]
