[{"timestamp":"2025-10-24T01:18:35.963Z","count":0,"uniques":0},{"timestamp":"2025-10-25T01:20:37.073Z","count":0,"uniques":0},{"timestamp":"2025-10-26T01:25:31.320Z","count":0,"uniques":0},{"timestamp":"2025-10-27T00:00:00.000Z","count":1,"uniques":1},{"timestamp":"2025-10-28T01:21:46.335Z","count":0,"uniques":0},{"timestamp":"2025-10-29T01:25:24.859Z","count":0,"uniques":0},{"timestamp":"2025-10-30T01:25:11.213Z","count":0,"uniques":0},{"timestamp":"2025-10-31T01:22:44.443Z","count":0,"uniques":0}]
