[{"timestamp":"2024-07-17T00:00:00.000Z","count":1,"uniques":1},{"timestamp":"2024-07-18T00:00:00.000Z","count":1,"uniques":1},{"timestamp":"2024-07-19T02:23:18.624Z","count":0,"uniques":0},{"timestamp":"2024-07-20T01:06:45.257Z","count":0,"uniques":0},{"timestamp":"2024-07-21T01:13:01.555Z","count":0,"uniques":0},{"timestamp":"2024-07-22T01:09:13.200Z","count":0,"uniques":0},{"timestamp":"2024-07-23T01:07:20.897Z","count":0,"uniques":0},{"timestamp":"2024-07-24T01:08:21.414Z","count":0,"uniques":0}]
