[{"timestamp":"2025-08-12T01:27:29.277Z","count":0,"uniques":0},{"timestamp":"2025-08-13T01:27:22.753Z","count":0,"uniques":0},{"timestamp":"2025-08-14T01:26:17.407Z","count":0,"uniques":0},{"timestamp":"2025-08-15T06:43:28.737Z","count":0,"uniques":0},{"timestamp":"2025-08-16T01:24:45.246Z","count":0,"uniques":0},{"timestamp":"2025-08-17T01:33:01.718Z","count":0,"uniques":0},{"timestamp":"2025-08-18T01:30:36.933Z","count":0,"uniques":0},{"timestamp":"2025-08-19T01:24:29.406Z","count":0,"uniques":0}]
