[{"timestamp":"2023-11-03T00:55:13.043Z","count":0,"uniques":0},{"timestamp":"2023-11-04T00:55:03.721Z","count":0,"uniques":0},{"timestamp":"2023-11-05T01:03:12.705Z","count":0,"uniques":0},{"timestamp":"2023-11-06T00:51:33.506Z","count":0,"uniques":0},{"timestamp":"2023-11-07T01:00:10.615Z","count":0,"uniques":0},{"timestamp":"2023-11-08T00:50:56.761Z","count":0,"uniques":0},{"timestamp":"2023-11-09T00:51:44.446Z","count":0,"uniques":0},{"timestamp":"2023-11-10T00:58:51.379Z","count":0,"uniques":0}]
