[{"timestamp":"2025-06-20T01:18:21.307Z","count":0,"uniques":0},{"timestamp":"2025-06-21T01:19:21.578Z","count":0,"uniques":0},{"timestamp":"2025-06-22T01:24:40.295Z","count":0,"uniques":0},{"timestamp":"2025-06-23T01:22:26.257Z","count":0,"uniques":0},{"timestamp":"2025-06-24T01:18:58.627Z","count":0,"uniques":0},{"timestamp":"2025-06-25T01:21:46.481Z","count":0,"uniques":0},{"timestamp":"2025-06-26T01:18:52.919Z","count":0,"uniques":0},{"timestamp":"2025-06-27T06:37:59.664Z","count":0,"uniques":0}]
