[{"timestamp":"2025-08-02T01:18:48.501Z","count":0,"uniques":0},{"timestamp":"2025-08-03T01:27:52.663Z","count":0,"uniques":0},{"timestamp":"2025-08-04T01:27:10.220Z","count":0,"uniques":0},{"timestamp":"2025-08-05T01:23:19.645Z","count":0,"uniques":0},{"timestamp":"2025-08-06T01:22:00.528Z","count":0,"uniques":0},{"timestamp":"2025-08-07T01:25:40.919Z","count":0,"uniques":0},{"timestamp":"2025-08-08T01:21:51.020Z","count":0,"uniques":0},{"timestamp":"2025-08-09T01:16:27.849Z","count":0,"uniques":0}]
