[{"timestamp":"2025-07-07T01:22:53.139Z","count":0,"uniques":0},{"timestamp":"2025-07-08T01:18:56.780Z","count":0,"uniques":0},{"timestamp":"2025-07-09T01:18:16.925Z","count":0,"uniques":0},{"timestamp":"2025-07-10T01:19:27.745Z","count":0,"uniques":0},{"timestamp":"2025-07-11T01:19:48.880Z","count":0,"uniques":0},{"timestamp":"2025-07-12T01:20:57.324Z","count":0,"uniques":0},{"timestamp":"2025-07-13T01:24:52.413Z","count":0,"uniques":0},{"timestamp":"2025-07-14T01:22:02.826Z","count":0,"uniques":0}]
