[{"timestamp":"2026-07-17T02:07:42.673Z","count":0,"uniques":0},{"timestamp":"2026-07-18T01:58:47.731Z","count":0,"uniques":0},{"timestamp":"2026-07-19T02:06:52.693Z","count":0,"uniques":0},{"timestamp":"2026-07-20T02:25:27.129Z","count":0,"uniques":0},{"timestamp":"2026-07-21T02:07:28.761Z","count":0,"uniques":0},{"timestamp":"2026-07-22T02:06:04.470Z","count":0,"uniques":0},{"timestamp":"2026-07-23T02:13:45.767Z","count":0,"uniques":0},{"timestamp":"2026-07-24T02:08:24.344Z","count":0,"uniques":0}]
