[{"timestamp":"2023-10-13T15:11:03.540Z","count":0,"uniques":0},{"timestamp":"2023-10-14T15:11:03.540Z","count":0,"uniques":0},{"timestamp":"2023-10-15T15:11:03.540Z","count":0,"uniques":0},{"timestamp":"2023-10-16T15:11:03.540Z","count":0,"uniques":0},{"timestamp":"2023-10-17T15:11:03.540Z","count":0,"uniques":0},{"timestamp":"2023-10-18T15:11:03.540Z","count":0,"uniques":0},{"timestamp":"2023-10-19T15:11:03.540Z","count":0,"uniques":0},{"timestamp":"2023-10-20T01:06:04.487Z","count":0,"uniques":0}]
