[{"timestamp":"2025-04-07T01:23:04.483Z","count":0,"uniques":0},{"timestamp":"2025-04-08T01:22:44.127Z","count":0,"uniques":0},{"timestamp":"2025-04-09T01:20:35.334Z","count":0,"uniques":0},{"timestamp":"2025-04-10T01:20:17.093Z","count":0,"uniques":0},{"timestamp":"2025-04-11T01:21:42.592Z","count":0,"uniques":0},{"timestamp":"2025-04-12T01:20:05.685Z","count":0,"uniques":0},{"timestamp":"2025-04-13T02:51:46.963Z","count":0,"uniques":0},{"timestamp":"2025-04-14T01:23:35.645Z","count":0,"uniques":0}]
