[{"timestamp":"2025-05-02T01:06:05.339Z","count":0,"uniques":0},{"timestamp":"2025-05-03T01:03:50.707Z","count":0,"uniques":0},{"timestamp":"2025-05-04T01:10:57.315Z","count":0,"uniques":0},{"timestamp":"2025-05-05T01:08:50.587Z","count":0,"uniques":0},{"timestamp":"2025-05-06T01:05:34.158Z","count":0,"uniques":0},{"timestamp":"2025-05-07T01:05:40.468Z","count":0,"uniques":0},{"timestamp":"2025-05-08T01:06:53.361Z","count":0,"uniques":0},{"timestamp":"2025-05-09T01:05:35.903Z","count":0,"uniques":0}]
