[{"timestamp":"2026-06-19T03:44:32.910Z","count":0,"uniques":0},{"timestamp":"2026-06-20T02:49:05.343Z","count":0,"uniques":0},{"timestamp":"2026-06-21T00:00:00.000Z","count":16,"uniques":1},{"timestamp":"2026-06-22T03:07:24.045Z","count":0,"uniques":0},{"timestamp":"2026-06-23T02:43:53.467Z","count":0,"uniques":0},{"timestamp":"2026-06-24T02:45:14.179Z","count":0,"uniques":0},{"timestamp":"2026-06-25T02:47:46.830Z","count":0,"uniques":0},{"timestamp":"2026-06-26T02:47:14.678Z","count":0,"uniques":0}]
