[{"timestamp":"2026-03-05T01:31:50.017Z","count":0,"uniques":0},{"timestamp":"2026-03-06T01:35:17.907Z","count":0,"uniques":0},{"timestamp":"2026-03-07T01:26:56.290Z","count":0,"uniques":0},{"timestamp":"2026-03-08T06:45:56.673Z","count":0,"uniques":0},{"timestamp":"2026-03-09T01:32:57.365Z","count":0,"uniques":0},{"timestamp":"2026-03-10T01:28:19.661Z","count":0,"uniques":0},{"timestamp":"2026-03-11T01:27:58.195Z","count":0,"uniques":0},{"timestamp":"2026-03-12T01:27:32.482Z","count":0,"uniques":0}]
