[{"timestamp":"2025-09-01T01:15:05.954Z","count":0,"uniques":0},{"timestamp":"2025-09-02T01:05:41.065Z","count":0,"uniques":0},{"timestamp":"2025-09-03T01:01:48.723Z","count":0,"uniques":0},{"timestamp":"2025-09-04T01:02:22.129Z","count":0,"uniques":0},{"timestamp":"2025-09-05T01:02:56.612Z","count":0,"uniques":0},{"timestamp":"2025-09-06T01:01:36.815Z","count":0,"uniques":0},{"timestamp":"2025-09-07T01:07:48.369Z","count":0,"uniques":0},{"timestamp":"2025-09-08T06:26:48.669Z","count":0,"uniques":0},{"timestamp":"2025-09-09T01:04:36.461Z","count":0,"uniques":0},{"timestamp":"2025-09-10T01:02:38.288Z","count":0,"uniques":0},{"timestamp":"2025-09-11T06:26:04.469Z","count":0,"uniques":0},{"timestamp":"2025-09-12T01:02:26.303Z","count":0,"uniques":0},{"timestamp":"2025-09-13T00:59:31.873Z","count":0,"uniques":0},{"timestamp":"2025-09-14T01:07:36.256Z","count":0,"uniques":0},{"timestamp":"2025-09-15T01:07:14.849Z","count":0,"uniques":0},{"timestamp":"2025-09-16T01:02:39.812Z","count":0,"uniques":0},{"timestamp":"2025-09-17T01:02:47.840Z","count":0,"uniques":0},{"timestamp":"2025-09-18T01:03:00.770Z","count":0,"uniques":0},{"timestamp":"2025-09-19T01:04:42.967Z","count":0,"uniques":0},{"timestamp":"2025-09-20T01:00:50.233Z","count":0,"uniques":0},{"timestamp":"2025-09-21T01:08:20.084Z","count":0,"uniques":0},{"timestamp":"2025-09-22T01:07:41.230Z","count":0,"uniques":0},{"timestamp":"2025-09-23T01:03:14.891Z","count":0,"uniques":0},{"timestamp":"2025-09-24T01:03:21.118Z","count":0,"uniques":0},{"timestamp":"2025-09-25T01:03:31.685Z","count":0,"uniques":0},{"timestamp":"2025-09-26T01:03:10.468Z","count":0,"uniques":0},{"timestamp":"2025-09-27T01:01:14.523Z","count":0,"uniques":0},{"timestamp":"2025-09-28T01:09:29.402Z","count":0,"uniques":0},{"timestamp":"2025-09-29T01:05:17.274Z","count":0,"uniques":0},{"timestamp":"2025-09-30T01:04:00.337Z","count":0,"uniques":0},{"timestamp":"2025-10-01T01:10:39.691Z","count":0,"uniques":0}]
