[{"timestamp":"2025-07-04T01:09:25.994Z","count":0,"uniques":0},{"timestamp":"2025-07-05T01:07:14.096Z","count":0,"uniques":0},{"timestamp":"2025-07-06T01:15:26.909Z","count":0,"uniques":0},{"timestamp":"2025-07-07T01:14:51.750Z","count":0,"uniques":0},{"timestamp":"2025-07-08T01:10:55.664Z","count":0,"uniques":0},{"timestamp":"2025-07-09T01:10:56.510Z","count":0,"uniques":0},{"timestamp":"2025-07-10T01:11:31.761Z","count":0,"uniques":0},{"timestamp":"2025-07-11T01:11:50.337Z","count":0,"uniques":0},{"timestamp":"2025-07-12T01:13:11.010Z","count":0,"uniques":0},{"timestamp":"2025-07-13T01:17:33.575Z","count":0,"uniques":0},{"timestamp":"2025-07-14T01:14:37.704Z","count":0,"uniques":0},{"timestamp":"2025-07-15T01:13:52.069Z","count":0,"uniques":0},{"timestamp":"2025-07-16T01:12:44.900Z","count":0,"uniques":0},{"timestamp":"2025-07-17T01:13:07.241Z","count":0,"uniques":0},{"timestamp":"2025-07-18T01:12:48.203Z","count":0,"uniques":0},{"timestamp":"2025-07-19T01:10:58.350Z","count":0,"uniques":0},{"timestamp":"2025-07-20T06:25:51.598Z","count":0,"uniques":0},{"timestamp":"2025-07-21T01:16:44.955Z","count":0,"uniques":0},{"timestamp":"2025-07-22T01:12:46.921Z","count":0,"uniques":0},{"timestamp":"2025-07-23T01:13:58.316Z","count":0,"uniques":0},{"timestamp":"2025-07-24T01:13:01.161Z","count":0,"uniques":0},{"timestamp":"2025-07-25T01:12:43.307Z","count":0,"uniques":0},{"timestamp":"2025-07-26T01:11:17.053Z","count":0,"uniques":0},{"timestamp":"2025-07-27T01:19:35.418Z","count":0,"uniques":0},{"timestamp":"2025-07-28T01:17:51.048Z","count":0,"uniques":0},{"timestamp":"2025-07-29T01:20:46.903Z","count":0,"uniques":0},{"timestamp":"2025-07-30T01:14:07.594Z","count":0,"uniques":0},{"timestamp":"2025-07-31T01:14:24.044Z","count":0,"uniques":0},{"timestamp":"2025-08-01T01:21:46.541Z","count":0,"uniques":0},{"timestamp":"2025-08-02T01:11:20.689Z","count":0,"uniques":0},{"timestamp":"2025-08-03T01:20:39.498Z","count":0,"uniques":0}]
