[{"timestamp":"2025-07-29T01:20:46.903Z","count":0,"uniques":0},{"timestamp":"2025-07-30T01:14:07.594Z","count":0,"uniques":0},{"timestamp":"2025-07-31T01:14:24.044Z","count":0,"uniques":0},{"timestamp":"2025-08-01T01:21:46.541Z","count":0,"uniques":0},{"timestamp":"2025-08-02T01:11:20.689Z","count":0,"uniques":0},{"timestamp":"2025-08-03T01:20:39.498Z","count":0,"uniques":0},{"timestamp":"2025-08-04T01:19:35.827Z","count":0,"uniques":0},{"timestamp":"2025-08-05T01:15:57.775Z","count":0,"uniques":0}]
