[{"timestamp":"2026-02-24T01:33:16.095Z","count":0,"uniques":0},{"timestamp":"2026-02-25T01:38:30.821Z","count":0,"uniques":0},{"timestamp":"2026-02-26T01:32:53.425Z","count":0,"uniques":0},{"timestamp":"2026-02-27T01:31:49.176Z","count":0,"uniques":0},{"timestamp":"2026-02-28T01:24:54.082Z","count":0,"uniques":0},{"timestamp":"2026-03-01T01:41:12.627Z","count":0,"uniques":0},{"timestamp":"2026-03-02T01:33:47.962Z","count":0,"uniques":0},{"timestamp":"2026-03-03T01:36:37.591Z","count":0,"uniques":0},{"timestamp":"2026-03-04T06:52:00.931Z","count":0,"uniques":0},{"timestamp":"2026-03-05T01:33:37.613Z","count":0,"uniques":0},{"timestamp":"2026-03-06T01:37:05.359Z","count":0,"uniques":0},{"timestamp":"2026-03-07T01:28:42.438Z","count":0,"uniques":0},{"timestamp":"2026-03-08T06:47:45.056Z","count":0,"uniques":0},{"timestamp":"2026-03-09T01:34:46.496Z","count":0,"uniques":0},{"timestamp":"2026-03-10T01:30:12.773Z","count":0,"uniques":0},{"timestamp":"2026-03-11T01:29:48.151Z","count":0,"uniques":0},{"timestamp":"2026-03-12T01:29:24.417Z","count":0,"uniques":0},{"timestamp":"2026-03-13T01:33:32.225Z","count":0,"uniques":0},{"timestamp":"2026-03-14T01:32:35.068Z","count":0,"uniques":0},{"timestamp":"2026-03-15T01:43:54.542Z","count":0,"uniques":0},{"timestamp":"2026-03-16T01:44:06.535Z","count":0,"uniques":0},{"timestamp":"2026-03-17T01:36:17.750Z","count":0,"uniques":0},{"timestamp":"2026-03-18T01:38:56.279Z","count":0,"uniques":0},{"timestamp":"2026-03-19T01:39:03.568Z","count":0,"uniques":0},{"timestamp":"2026-03-20T01:34:29.201Z","count":0,"uniques":0},{"timestamp":"2026-03-21T01:28:24.111Z","count":0,"uniques":0},{"timestamp":"2026-03-22T01:38:46.088Z","count":0,"uniques":0},{"timestamp":"2026-03-23T01:40:36.943Z","count":0,"uniques":0},{"timestamp":"2026-03-24T01:34:04.951Z","count":0,"uniques":0},{"timestamp":"2026-03-25T01:37:16.571Z","count":0,"uniques":0},{"timestamp":"2026-03-26T01:42:50.625Z","count":0,"uniques":0}]
