[{"timestamp":"2026-03-10T01:20:18.322Z","count":0,"uniques":0},{"timestamp":"2026-03-11T01:20:12.755Z","count":0,"uniques":0},{"timestamp":"2026-03-12T01:19:43.669Z","count":0,"uniques":0},{"timestamp":"2026-03-13T01:23:54.177Z","count":0,"uniques":0},{"timestamp":"2026-03-14T01:22:36.457Z","count":0,"uniques":0},{"timestamp":"2026-03-15T01:34:31.307Z","count":0,"uniques":0},{"timestamp":"2026-03-16T01:34:17.684Z","count":0,"uniques":0},{"timestamp":"2026-03-17T01:26:11.931Z","count":0,"uniques":0}]
