[{"timestamp":"2026-02-25T01:42:12.601Z","count":0,"uniques":0},{"timestamp":"2026-02-26T01:36:27.887Z","count":0,"uniques":0},{"timestamp":"2026-02-27T01:35:31.047Z","count":0,"uniques":0},{"timestamp":"2026-02-28T01:28:15.737Z","count":0,"uniques":0},{"timestamp":"2026-03-01T01:44:43.654Z","count":0,"uniques":0},{"timestamp":"2026-03-02T01:37:25.560Z","count":0,"uniques":0},{"timestamp":"2026-03-03T01:40:16.976Z","count":0,"uniques":0},{"timestamp":"2026-03-04T06:55:42.739Z","count":0,"uniques":0},{"timestamp":"2026-03-05T01:37:09.608Z","count":0,"uniques":0},{"timestamp":"2026-03-06T01:40:42.452Z","count":0,"uniques":0},{"timestamp":"2026-03-07T01:32:14.289Z","count":0,"uniques":0},{"timestamp":"2026-03-08T06:51:20.901Z","count":0,"uniques":0},{"timestamp":"2026-03-09T01:38:25.089Z","count":0,"uniques":0},{"timestamp":"2026-03-10T01:34:01.733Z","count":0,"uniques":0},{"timestamp":"2026-03-11T01:33:29.384Z","count":0,"uniques":0},{"timestamp":"2026-03-12T01:33:07.695Z","count":0,"uniques":0},{"timestamp":"2026-03-13T01:37:15.509Z","count":0,"uniques":0},{"timestamp":"2026-03-14T01:36:27.050Z","count":0,"uniques":0},{"timestamp":"2026-03-15T01:47:30.496Z","count":0,"uniques":0},{"timestamp":"2026-03-16T01:47:52.771Z","count":0,"uniques":0},{"timestamp":"2026-03-17T01:40:07.069Z","count":0,"uniques":0},{"timestamp":"2026-03-18T01:42:32.813Z","count":0,"uniques":0},{"timestamp":"2026-03-19T01:42:37.529Z","count":0,"uniques":0},{"timestamp":"2026-03-20T01:38:06.686Z","count":0,"uniques":0},{"timestamp":"2026-03-21T01:31:44.180Z","count":0,"uniques":0},{"timestamp":"2026-03-22T01:42:26.488Z","count":0,"uniques":0},{"timestamp":"2026-03-23T00:00:00.000Z","count":1,"uniques":1},{"timestamp":"2026-03-24T01:37:56.761Z","count":0,"uniques":0},{"timestamp":"2026-03-25T01:40:49.344Z","count":0,"uniques":0},{"timestamp":"2026-03-26T01:46:26.839Z","count":0,"uniques":0},{"timestamp":"2026-03-27T01:46:58.318Z","count":0,"uniques":0}]
