[{"timestamp":"2024-03-14T00:56:03.182Z","count":0,"uniques":0},{"timestamp":"2024-03-15T00:54:42.455Z","count":0,"uniques":0},{"timestamp":"2024-03-16T00:53:39.130Z","count":0,"uniques":0},{"timestamp":"2024-03-17T00:58:49.582Z","count":0,"uniques":0},{"timestamp":"2024-03-18T00:57:16.465Z","count":0,"uniques":0},{"timestamp":"2024-03-19T00:56:47.964Z","count":0,"uniques":0},{"timestamp":"2024-03-20T00:55:35.958Z","count":0,"uniques":0},{"timestamp":"2024-03-21T00:55:40.056Z","count":0,"uniques":0}]
