[{"timestamp":"2025-04-28T06:42:58.263Z","count":0,"uniques":0},{"timestamp":"2025-04-29T01:15:48.319Z","count":0,"uniques":0},{"timestamp":"2025-04-30T01:16:47.952Z","count":0,"uniques":0},{"timestamp":"2025-05-01T01:22:04.971Z","count":0,"uniques":0},{"timestamp":"2025-05-02T01:19:06.337Z","count":0,"uniques":0},{"timestamp":"2025-05-03T01:15:33.033Z","count":0,"uniques":0},{"timestamp":"2025-05-04T01:22:31.546Z","count":0,"uniques":0},{"timestamp":"2025-05-05T01:21:35.093Z","count":0,"uniques":0}]
