[{"timestamp":"2024-10-25T00:59:37.297Z","count":0,"uniques":0},{"timestamp":"2024-10-26T00:57:06.920Z","count":0,"uniques":0},{"timestamp":"2024-10-27T01:03:34.869Z","count":0,"uniques":0},{"timestamp":"2024-10-28T01:00:55.990Z","count":0,"uniques":0},{"timestamp":"2024-10-29T01:00:43.606Z","count":0,"uniques":0},{"timestamp":"2024-10-30T01:00:17.283Z","count":0,"uniques":0},{"timestamp":"2024-10-31T00:59:26.357Z","count":0,"uniques":0},{"timestamp":"2024-11-01T01:03:24.899Z","count":0,"uniques":0}]
