[{"timestamp":"2025-06-03T01:12:00.780Z","count":0,"uniques":0},{"timestamp":"2025-06-04T01:11:14.724Z","count":0,"uniques":0},{"timestamp":"2025-06-05T06:29:21.344Z","count":0,"uniques":0},{"timestamp":"2025-06-06T01:10:46.297Z","count":0,"uniques":0},{"timestamp":"2025-06-07T01:10:35.492Z","count":0,"uniques":0},{"timestamp":"2025-06-08T01:17:09.006Z","count":0,"uniques":0},{"timestamp":"2025-06-09T01:14:08.576Z","count":0,"uniques":0},{"timestamp":"2025-06-10T01:11:11.798Z","count":0,"uniques":0}]
