[{"timestamp":"2024-01-19T00:55:37.053Z","count":0,"uniques":0},{"timestamp":"2024-01-20T00:55:30.003Z","count":0,"uniques":0},{"timestamp":"2024-01-21T00:59:53.831Z","count":0,"uniques":0},{"timestamp":"2024-01-22T00:59:42.211Z","count":0,"uniques":0},{"timestamp":"2024-01-23T00:56:52.165Z","count":0,"uniques":0},{"timestamp":"2024-01-24T00:57:13.134Z","count":0,"uniques":0},{"timestamp":"2024-01-25T00:56:30.364Z","count":0,"uniques":0},{"timestamp":"2024-01-26T00:55:18.414Z","count":0,"uniques":0},{"timestamp":"2024-01-27T00:54:19.515Z","count":0,"uniques":0},{"timestamp":"2024-01-28T00:57:03.599Z","count":0,"uniques":0},{"timestamp":"2024-01-29T00:53:47.053Z","count":0,"uniques":0},{"timestamp":"2024-01-30T00:53:01.447Z","count":0,"uniques":0},{"timestamp":"2024-01-31T00:55:03.074Z","count":0,"uniques":0},{"timestamp":"2024-02-01T00:55:38.162Z","count":0,"uniques":0},{"timestamp":"2024-02-02T00:54:01.929Z","count":0,"uniques":0},{"timestamp":"2024-02-03T00:53:24.246Z","count":0,"uniques":0},{"timestamp":"2024-02-04T00:56:13.930Z","count":0,"uniques":0},{"timestamp":"2024-02-05T00:55:35.200Z","count":0,"uniques":0},{"timestamp":"2024-02-06T00:54:58.397Z","count":0,"uniques":0},{"timestamp":"2024-02-07T00:51:52.740Z","count":0,"uniques":0},{"timestamp":"2024-02-08T00:53:39.611Z","count":0,"uniques":0},{"timestamp":"2024-02-09T00:54:33.427Z","count":0,"uniques":0},{"timestamp":"2024-02-10T00:52:09.825Z","count":0,"uniques":0},{"timestamp":"2024-02-11T00:57:11.109Z","count":0,"uniques":0},{"timestamp":"2024-02-12T00:54:13.719Z","count":0,"uniques":0},{"timestamp":"2024-02-13T00:53:38.209Z","count":0,"uniques":0},{"timestamp":"2024-02-14T00:54:33.126Z","count":0,"uniques":0},{"timestamp":"2024-02-15T00:55:42.708Z","count":0,"uniques":0},{"timestamp":"2024-02-16T00:55:19.026Z","count":0,"uniques":0},{"timestamp":"2024-02-17T00:52:46.448Z","count":0,"uniques":0},{"timestamp":"2024-02-18T00:57:53.380Z","count":0,"uniques":0}]
