[{"timestamp":"2025-05-23T01:19:48.863Z","count":0,"uniques":0},{"timestamp":"2025-05-24T01:16:02.227Z","count":0,"uniques":0},{"timestamp":"2025-05-25T01:24:34.581Z","count":0,"uniques":0},{"timestamp":"2025-05-26T01:20:36.972Z","count":0,"uniques":0},{"timestamp":"2025-05-27T01:16:06.995Z","count":0,"uniques":0},{"timestamp":"2025-05-28T01:17:43.735Z","count":0,"uniques":0},{"timestamp":"2025-05-29T01:17:39.291Z","count":0,"uniques":0},{"timestamp":"2025-05-30T01:17:07.993Z","count":0,"uniques":0},{"timestamp":"2025-05-31T01:18:44.181Z","count":0,"uniques":0},{"timestamp":"2025-06-01T01:29:51.694Z","count":0,"uniques":0},{"timestamp":"2025-06-02T01:20:39.807Z","count":0,"uniques":0},{"timestamp":"2025-06-03T01:20:39.833Z","count":0,"uniques":0},{"timestamp":"2025-06-04T01:19:29.184Z","count":0,"uniques":0},{"timestamp":"2025-06-05T06:38:09.439Z","count":0,"uniques":0},{"timestamp":"2025-06-06T01:18:51.982Z","count":0,"uniques":0},{"timestamp":"2025-06-07T01:19:16.949Z","count":0,"uniques":0},{"timestamp":"2025-06-08T01:25:46.819Z","count":0,"uniques":0},{"timestamp":"2025-06-09T01:22:14.806Z","count":0,"uniques":0},{"timestamp":"2025-06-10T01:19:00.006Z","count":0,"uniques":0},{"timestamp":"2025-06-11T01:19:05.800Z","count":0,"uniques":0},{"timestamp":"2025-06-12T01:20:24.710Z","count":0,"uniques":0},{"timestamp":"2025-06-13T01:19:18.073Z","count":0,"uniques":0},{"timestamp":"2025-06-14T01:17:10.548Z","count":0,"uniques":0},{"timestamp":"2025-06-15T01:25:43.161Z","count":0,"uniques":0},{"timestamp":"2025-06-16T01:21:52.065Z","count":0,"uniques":0},{"timestamp":"2025-06-17T01:18:51.455Z","count":0,"uniques":0},{"timestamp":"2025-06-18T01:20:38.608Z","count":0,"uniques":0},{"timestamp":"2025-06-19T01:18:49.773Z","count":0,"uniques":0},{"timestamp":"2025-06-20T01:18:41.512Z","count":0,"uniques":0},{"timestamp":"2025-06-21T01:19:43.857Z","count":0,"uniques":0},{"timestamp":"2025-06-22T01:25:01.480Z","count":0,"uniques":0}]
