[{"timestamp":"2025-01-07T01:09:02.542Z","count":0,"uniques":0},{"timestamp":"2025-01-08T01:09:10.543Z","count":0,"uniques":0},{"timestamp":"2025-01-09T01:08:44.067Z","count":0,"uniques":0},{"timestamp":"2025-01-10T01:12:30.492Z","count":0,"uniques":0},{"timestamp":"2025-01-11T01:10:32.057Z","count":0,"uniques":0},{"timestamp":"2025-01-12T01:14:10.227Z","count":0,"uniques":0},{"timestamp":"2025-01-13T01:14:07.923Z","count":0,"uniques":0},{"timestamp":"2025-01-14T01:06:33.615Z","count":0,"uniques":0}]
