[{"timestamp":"2024-12-05T01:00:17.691Z","count":0,"uniques":0},{"timestamp":"2024-12-06T01:00:03.324Z","count":0,"uniques":0},{"timestamp":"2024-12-07T00:59:00.278Z","count":0,"uniques":0},{"timestamp":"2024-12-08T01:04:09.689Z","count":0,"uniques":0},{"timestamp":"2024-12-09T01:01:44.179Z","count":0,"uniques":0},{"timestamp":"2024-12-10T01:01:08.752Z","count":0,"uniques":0},{"timestamp":"2024-12-11T00:59:53.463Z","count":0,"uniques":0},{"timestamp":"2024-12-12T00:59:41.241Z","count":0,"uniques":0},{"timestamp":"2024-12-13T01:00:50.282Z","count":0,"uniques":0},{"timestamp":"2024-12-14T00:58:47.061Z","count":0,"uniques":0},{"timestamp":"2024-12-15T01:04:21.140Z","count":0,"uniques":0},{"timestamp":"2024-12-16T01:02:03.204Z","count":0,"uniques":0},{"timestamp":"2024-12-17T00:59:58.532Z","count":0,"uniques":0},{"timestamp":"2024-12-18T00:57:59.796Z","count":0,"uniques":0},{"timestamp":"2024-12-19T00:00:00.000Z","count":1,"uniques":1},{"timestamp":"2024-12-20T00:55:58.801Z","count":0,"uniques":0},{"timestamp":"2024-12-21T00:00:00.000Z","count":4,"uniques":1},{"timestamp":"2024-12-22T00:59:48.525Z","count":0,"uniques":0},{"timestamp":"2024-12-23T00:56:53.279Z","count":0,"uniques":0},{"timestamp":"2024-12-24T00:55:32.568Z","count":0,"uniques":0},{"timestamp":"2024-12-25T00:54:42.653Z","count":0,"uniques":0},{"timestamp":"2024-12-26T00:55:22.546Z","count":0,"uniques":0},{"timestamp":"2024-12-27T00:55:08.212Z","count":0,"uniques":0},{"timestamp":"2024-12-28T00:54:05.915Z","count":0,"uniques":0},{"timestamp":"2024-12-29T01:00:20.348Z","count":0,"uniques":0},{"timestamp":"2024-12-30T00:57:14.461Z","count":0,"uniques":0},{"timestamp":"2024-12-31T00:55:40.229Z","count":0,"uniques":0},{"timestamp":"2025-01-01T01:00:31.395Z","count":0,"uniques":0},{"timestamp":"2025-01-02T00:54:54.644Z","count":0,"uniques":0},{"timestamp":"2025-01-03T00:55:37.241Z","count":0,"uniques":0},{"timestamp":"2025-01-04T00:54:51.306Z","count":0,"uniques":0}]
