[{"timestamp":"2024-01-07T01:08:42.601Z","count":0,"uniques":0},{"timestamp":"2024-01-08T01:05:31.009Z","count":0,"uniques":0},{"timestamp":"2024-01-09T01:04:25.912Z","count":0,"uniques":0},{"timestamp":"2024-01-10T01:07:20.735Z","count":0,"uniques":0},{"timestamp":"2024-01-11T01:07:54.097Z","count":0,"uniques":0},{"timestamp":"2024-01-12T01:04:15.569Z","count":0,"uniques":0},{"timestamp":"2024-01-13T01:03:49.397Z","count":0,"uniques":0},{"timestamp":"2024-01-14T01:07:14.899Z","count":0,"uniques":0},{"timestamp":"2024-01-15T01:06:30.525Z","count":0,"uniques":0},{"timestamp":"2024-01-16T01:05:30.287Z","count":0,"uniques":0},{"timestamp":"2024-01-17T01:04:29.079Z","count":0,"uniques":0},{"timestamp":"2024-01-18T01:03:40.979Z","count":0,"uniques":0},{"timestamp":"2024-01-19T01:04:27.891Z","count":0,"uniques":0},{"timestamp":"2024-01-20T01:04:46.399Z","count":0,"uniques":0},{"timestamp":"2024-01-21T01:09:17.299Z","count":0,"uniques":0},{"timestamp":"2024-01-22T01:09:26.794Z","count":0,"uniques":0},{"timestamp":"2024-01-23T01:05:50.742Z","count":0,"uniques":0},{"timestamp":"2024-01-24T01:06:44.027Z","count":0,"uniques":0},{"timestamp":"2024-01-25T01:05:34.017Z","count":0,"uniques":0},{"timestamp":"2024-01-26T01:05:25.264Z","count":0,"uniques":0},{"timestamp":"2024-01-27T01:04:07.004Z","count":0,"uniques":0},{"timestamp":"2024-01-28T01:07:00.085Z","count":0,"uniques":0},{"timestamp":"2024-01-29T01:03:06.550Z","count":0,"uniques":0},{"timestamp":"2024-01-30T01:01:50.941Z","count":0,"uniques":0},{"timestamp":"2024-01-31T01:04:43.917Z","count":0,"uniques":0},{"timestamp":"2024-02-01T01:04:45.358Z","count":0,"uniques":0},{"timestamp":"2024-02-02T01:03:16.376Z","count":0,"uniques":0},{"timestamp":"2024-02-03T01:02:39.266Z","count":0,"uniques":0},{"timestamp":"2024-02-04T01:05:07.561Z","count":0,"uniques":0},{"timestamp":"2024-02-05T01:04:58.751Z","count":0,"uniques":0},{"timestamp":"2024-02-06T01:04:45.019Z","count":0,"uniques":0}]
