[{"timestamp":"2024-03-28T00:47:45.647Z","count":0,"uniques":0},{"timestamp":"2024-03-29T00:47:32.708Z","count":0,"uniques":0},{"timestamp":"2024-03-30T00:46:42.814Z","count":0,"uniques":0},{"timestamp":"2024-03-31T00:50:39.519Z","count":0,"uniques":0},{"timestamp":"2024-04-01T00:50:46.869Z","count":0,"uniques":0},{"timestamp":"2024-04-02T00:50:50.446Z","count":0,"uniques":0},{"timestamp":"2024-04-03T00:46:15.124Z","count":0,"uniques":0},{"timestamp":"2024-04-04T00:49:31.142Z","count":0,"uniques":0},{"timestamp":"2024-04-05T00:47:20.854Z","count":0,"uniques":0},{"timestamp":"2024-04-06T00:45:58.330Z","count":0,"uniques":0},{"timestamp":"2024-04-07T00:50:58.000Z","count":0,"uniques":0},{"timestamp":"2024-04-08T00:48:11.621Z","count":0,"uniques":0},{"timestamp":"2024-04-09T00:48:18.518Z","count":0,"uniques":0},{"timestamp":"2024-04-10T00:49:27.267Z","count":0,"uniques":0},{"timestamp":"2024-04-11T00:48:48.625Z","count":0,"uniques":0},{"timestamp":"2024-04-12T00:47:28.910Z","count":0,"uniques":0},{"timestamp":"2024-04-13T00:41:02.988Z","count":0,"uniques":0},{"timestamp":"2024-04-14T00:44:55.411Z","count":0,"uniques":0},{"timestamp":"2024-04-15T03:07:22.649Z","count":0,"uniques":0},{"timestamp":"2024-04-16T00:46:50.984Z","count":0,"uniques":0},{"timestamp":"2024-04-17T00:48:48.577Z","count":0,"uniques":0},{"timestamp":"2024-04-18T00:48:13.224Z","count":0,"uniques":0},{"timestamp":"2024-04-19T00:48:38.268Z","count":0,"uniques":0},{"timestamp":"2024-04-20T00:47:48.228Z","count":0,"uniques":0},{"timestamp":"2024-04-21T00:50:55.215Z","count":0,"uniques":0},{"timestamp":"2024-04-22T00:50:04.874Z","count":0,"uniques":0},{"timestamp":"2024-04-23T00:47:43.669Z","count":0,"uniques":0},{"timestamp":"2024-04-24T00:47:32.939Z","count":0,"uniques":0},{"timestamp":"2024-04-25T00:51:17.034Z","count":0,"uniques":0},{"timestamp":"2024-04-26T00:48:23.882Z","count":0,"uniques":0},{"timestamp":"2024-04-27T00:47:41.475Z","count":0,"uniques":0}]
