[{"timestamp":"2025-10-12T01:08:37.998Z","count":0,"uniques":0},{"timestamp":"2025-10-13T01:09:17.686Z","count":0,"uniques":0},{"timestamp":"2025-10-14T01:05:33.539Z","count":0,"uniques":0},{"timestamp":"2025-10-15T01:07:53.330Z","count":0,"uniques":0},{"timestamp":"2025-10-16T01:07:52.404Z","count":0,"uniques":0},{"timestamp":"2025-10-17T01:06:24.641Z","count":0,"uniques":0},{"timestamp":"2025-10-18T01:04:00.547Z","count":0,"uniques":0},{"timestamp":"2025-10-19T01:13:12.337Z","count":0,"uniques":0}]
