[{"timestamp":"2025-02-03T01:01:34.829Z","count":0,"uniques":0},{"timestamp":"2025-02-04T01:01:35.041Z","count":0,"uniques":0},{"timestamp":"2025-02-05T01:01:11.767Z","count":0,"uniques":0},{"timestamp":"2025-02-06T01:01:16.234Z","count":0,"uniques":0},{"timestamp":"2025-02-07T01:01:29.172Z","count":0,"uniques":0},{"timestamp":"2025-02-08T01:00:06.585Z","count":0,"uniques":0},{"timestamp":"2025-02-09T01:04:29.888Z","count":0,"uniques":0},{"timestamp":"2025-02-10T06:25:18.434Z","count":0,"uniques":0}]
