[{"timestamp":"2025-10-07T01:16:48.290Z","count":0,"uniques":0},{"timestamp":"2025-10-08T01:16:34.529Z","count":0,"uniques":0},{"timestamp":"2025-10-09T01:17:54.976Z","count":0,"uniques":0},{"timestamp":"2025-10-10T01:17:39.607Z","count":0,"uniques":0},{"timestamp":"2025-10-11T01:16:09.874Z","count":0,"uniques":0},{"timestamp":"2025-10-12T01:21:28.398Z","count":0,"uniques":0},{"timestamp":"2025-10-13T01:21:21.467Z","count":0,"uniques":0},{"timestamp":"2025-10-14T01:18:00.097Z","count":0,"uniques":0}]
