[{"timestamp":"2024-11-04T01:19:06.407Z","count":0,"uniques":0},{"timestamp":"2024-11-05T01:18:09.352Z","count":0,"uniques":0},{"timestamp":"2024-11-06T01:18:36.679Z","count":0,"uniques":0},{"timestamp":"2024-11-07T01:18:47.047Z","count":0,"uniques":0},{"timestamp":"2024-11-08T01:15:10.678Z","count":0,"uniques":0},{"timestamp":"2024-11-09T01:17:01.643Z","count":0,"uniques":0},{"timestamp":"2024-11-10T01:19:57.688Z","count":0,"uniques":0},{"timestamp":"2024-11-11T01:17:54.110Z","count":0,"uniques":0}]
