[{"timestamp":"2025-06-22T01:27:26.828Z","count":0,"uniques":0},{"timestamp":"2025-06-23T01:25:09.739Z","count":0,"uniques":0},{"timestamp":"2025-06-24T01:21:43.055Z","count":0,"uniques":0},{"timestamp":"2025-06-25T01:24:51.616Z","count":0,"uniques":0},{"timestamp":"2025-06-26T01:21:38.400Z","count":0,"uniques":0},{"timestamp":"2025-06-27T06:40:59.720Z","count":0,"uniques":0},{"timestamp":"2025-06-28T01:20:51.852Z","count":0,"uniques":0},{"timestamp":"2025-06-29T01:30:47.124Z","count":0,"uniques":0}]
