[{"timestamp":"2024-08-10T00:54:32.420Z","count":0,"uniques":0},{"timestamp":"2024-08-11T00:59:53.798Z","count":0,"uniques":0},{"timestamp":"2024-08-12T00:57:40.845Z","count":0,"uniques":0},{"timestamp":"2024-08-13T00:55:38.267Z","count":0,"uniques":0},{"timestamp":"2024-08-14T00:54:48.226Z","count":0,"uniques":0},{"timestamp":"2024-08-15T00:54:36.112Z","count":0,"uniques":0},{"timestamp":"2024-08-16T00:54:38.720Z","count":0,"uniques":0},{"timestamp":"2024-08-17T00:54:05.377Z","count":0,"uniques":0}]
