[{"timestamp":"2023-12-13T00:52:20.815Z","count":0,"uniques":0},{"timestamp":"2023-12-14T00:51:16.443Z","count":0,"uniques":0},{"timestamp":"2023-12-15T00:53:03.996Z","count":0,"uniques":0},{"timestamp":"2023-12-16T00:50:56.555Z","count":0,"uniques":0},{"timestamp":"2023-12-17T00:56:20.681Z","count":0,"uniques":0},{"timestamp":"2023-12-18T00:52:54.574Z","count":0,"uniques":0},{"timestamp":"2023-12-19T00:51:47.690Z","count":0,"uniques":0},{"timestamp":"2023-12-20T00:45:25.203Z","count":0,"uniques":0}]
