[{"timestamp":"2024-10-09T01:05:58.221Z","count":0,"uniques":0},{"timestamp":"2024-10-10T01:05:10.462Z","count":0,"uniques":0},{"timestamp":"2024-10-11T01:04:41.687Z","count":0,"uniques":0},{"timestamp":"2024-10-12T01:03:33.826Z","count":0,"uniques":0},{"timestamp":"2024-10-13T01:09:02.731Z","count":0,"uniques":0},{"timestamp":"2024-10-14T01:06:50.334Z","count":0,"uniques":0},{"timestamp":"2024-10-15T01:05:55.778Z","count":0,"uniques":0},{"timestamp":"2024-10-16T01:06:07.019Z","count":0,"uniques":0}]
